slg_setup/__init__.py
slg_setup/get_script_files.py
slg_setup-1.0.2.dist-info/METADATA
slg_setup-1.0.2.dist-info/WHEEL
slg_setup-1.0.2.dist-info/top_level.txt
slg_setup-1.0.2.dist-info/RECORD
